<?xml version="1.0" encoding="UTF-8"?>
<!DOCTYPE properties SYSTEM "http://java.sun.com/dtd/properties.dtd">

<!-- $Id: LangResource_en.xml,v 1.75 2006/07/26 04:03:05 biliang Exp $ -->

<properties>
    <comment>The English Language Resource Bundle for eWork 7.0 Web Server</comment>

    <entry key="exception.null.pointer">The network is busy now! Please try again later! (NP) ({0})</entry>
    <entry key="exception.runtime">The network is busy now! Please try again later! (RT) ({0})</entry>
    <entry key="exception.sensiwords">The network is busy now! Please try again later! (SW)</entry>
    <entry key="exception.network">The network is busy now! Please try again later! (IO)</entry>
    <entry key="exception.blank">{0}</entry>
    <entry key="exception.entity.missing">{0} {1} was not found! </entry>
    <entry key="exception.entity.exist">{0} &lt;b&gt;{1}&lt;/b&gt; has already existed! </entry>
    <entry key="exception.entity.paused">{0} &lt;b&gt;{1}&lt;/b&gt; has been paused! </entry>
    <entry key="exception.invalid.property">The {0} &lt;b&gt;{1}&lt;/b&gt; you input is invalid! </entry>
    <entry key="exception.id">You haven't provided a correct ID, or selected any entries in the listing table! </entry>
    <entry key="exception.login.failed">Login failed! </entry>
    <entry key="exception.login.failed.reason">Login failed! {0}</entry>
    <entry key="exception.password.unmatch">The password does not match! </entry>
    <entry key="exception.password.invalid">The password is not correct! </entry>
    <entry key="exception.urlnotfound">The page you requested does not exist or is under maintainance! Please come back later! </entry>
    <entry key="exception.invalid.strtoolong">The &lt;b&gt;{0}&lt;/b&gt; you input is too long. This is limited in length of &lt;b&gt;{1}&lt;/b&gt; Byte! </entry>
    <entry key="exception.dept.deleteroot">The root department is not allowed to be deleted! </entry>
    <entry key="exception.tree.rootmissing">The root department of Virtual Server &lt;b&gt;{0}&lt;/b&gt; does not exist! </entry>
    <entry key="exception.group.rootdelete">The default administrator of the virtual-server was not allowed to be deleted! </entry>
    <entry key="exception.group.private">Group &lt;b&gt;{0}&lt;/b&gt; has been set to be private, please choose another one which is public! </entry>
    <entry key="exception.pos.nodef">The default position does not exist! </entry>
    <entry key="exception.socket.offline">The network is busy now! Please try again later! (SO)</entry>
    <entry key="exception.chinapay.build">Chinapay security key building failed! </entry>
    <entry key="exception.chinapay.failed">ChinaPay verify failed! </entry>
    <entry key="exception.chinapay.verify.failed">ChinaPay verified failed! </entry>
    <entry key="exception.payment.nopaymethod">Please select one pay method! </entry>
    <entry key="exception.biz_service.wrongtime">Time should be greater than current time.</entry>
    <entry key="exception.biz_service.service">Biz Service.</entry>
    <entry key="exception.biz_service.exited">The service have exited.Please choose other service.</entry>
    <entry key="exception.biz.reg.userbonused">The bonus of registration has been reclaimed! </entry>
    <entry key="exception.biz.reg.mobilebonused">Mobile No. &lt;b&gt;{0}&lt;/b&gt; has been bound to another user! </entry>
    <entry key="exception.user.upgrade">We're sorry but your account &lt;b&gt;{0}&lt;/b&gt; cannot upgrade to eLink 2006 automatically this moment. Your account has been recorded and scheduled to be updated soon! </entry>
    <entry key="exception.user.fetchpwd.nullquestion">We're sorry but your password cannot be reset due to the absence of password question! </entry>
    <entry key="exception.chinapay.diff">We're sorry，your payment amount &lt;b&gt;{0}&lt;/b&gt; is different from we have received amount &lt;b&gt;{1}&lt;/b&gt;!</entry>
    <entry key="exception.chinapay.repay">Please don't pay more times!</entry>
    <entry key="exception.chinapay.repay.forbidden">Forbidden repay!</entry>
    <entry key="exception.fenix.region.joined">You have joined this forum!</entry>
    <entry key="exception.user.join.multiple">Forbiden join yourself as fiend!</entry>
    <entry key="exception.login.deny">{0} login deny!</entry>
    <entry key="exception.overflow">The info "{0}" length more than max length!</entry>
    
    
    <entry key="msg.ok">{0} succeeded! </entry>
    <entry key="msg.not.suport">Do Not Suport This Operation.</entry>
    <entry key="msg.failed">{0} failed! </entry>
    <entry key="msg.update">Information modification for  {0} &lt;b&gt;{1}&lt;/b&gt;</entry>
    <entry key="msg.create">{0} &lt;b&gt;{1}&lt;/b&gt; creating</entry>
    <entry key="msg.delete">Deleting of &lt;b&gt;{0}&lt;/b&gt; {1}(s)</entry>
    <entry key="msg.move">Movement of &lt;b&gt;{0}&lt;/b&gt; {1}(s)</entry>
    <entry key="msg.register">Register </entry>

    <entry key="msg.admin.create">Administrator &lt;b&gt;{0}&lt;/b&gt; creating</entry>
    <entry key="msg.admin.update">Information modification for administrator &lt;b&gt;{0}&lt;/b&gt; </entry>
    <entry key="msg.admin.delete">&lt;b&gt;{0}&lt;/b&gt; administrator(s) deleting</entry>
    <entry key="msg.meeting.update">Information modificationfor netmeeting &lt;b&gt;{0}&lt;/b&gt; </entry>
    <entry key="msg.meeting.delete">&lt;b&gt;{0}&lt;/b&gt; netmeeting(s) deleting</entry>
    <entry key="msg.user.create">User &lt;b&gt;{0}&lt;/b&gt; has been created successfully! You can create serveral positions for this user either immeidately, or later by "Organization - Users - Create Position". </entry>
    <entry key="msg.user.update">User info / password modification of user &lt;b&gt;{0}&lt;/b&gt;</entry>
    <entry key="msg.user.delete">&lt;b&gt;{0}&lt;/b&gt; users deleting</entry>
    <entry key="msg.user.invite">Friend inviting message sending</entry>
    <entry key="msg.dept.update">Department modification of &lt;b&gt;{0}&lt;/b&gt;</entry>
    <entry key="msg.dept.create">Department creation of &lt;b&gt;{0}&lt;/b&gt;</entry>
    <entry key="msg.tree.reorder">Tree nodes re-ordering</entry>
    <entry key="msg.tree.delete">&lt;b&gt;{0}&lt;/b&gt; tree nodes deleting</entry>
    <entry key="msg.tree.createuserpos">A new position of &lt;b&gt;{2}&lt;/b&gt; has been created for user &lt;b&gt;{0}&lt;/b&gt; in department &lt;b&gt;{1}&lt;/b&gt;! You can create more positions for this user, or go back to the position list. </entry>
    <entry key="msg.tree.updateuserpos">User position &lt;b&gt;{0}&lt;/b&gt; modification</entry>
    <entry key="msg.payment.delete">&lt;b&gt;{0}&lt;/b&gt; payments delete.</entry>
    <entry key="msg.payment.pay">Payment</entry>
    <entry key="msg.upgrade.publish">Upgrade version has been published successfully! </entry>
    <entry key="msg.fenix.region.delete">Forum &lt;b&gt;"{0}"&lt;/b&gt; delete </entry>
    <entry key="msg.fenix.region.join">Join Forum &lt;b&gt;"{0}"&lt;/b&gt; </entry>
    <entry key="msg.upgrade.scanning">System is scanning the upgrade files, please click "OK" button to set the operations of files! </entry>

    <entry key="msg.service.user.reg.bonus">Your cellphone No. has been verified successfully! Your account has been charged with &lt;b&gt;{0} Kon&lt;/b&gt;! </entry>

    <entry key="msg.user.fetchpwd">Your new password is &lt;b&gt;{0}&lt;/b&gt;, which can be changed after you signed-in with it! </entry>
    <entry key="msg.noentry">Nothing found to display.</entry>
    

    <entry key="entity.admin">Administrator</entry>
    <entry key="entity.user">User</entry>
    <entry key="entity.user.old">User of eLink 2005 / eWork 6.x</entry>
    <entry key="entity.user_account">User Account</entry>
    <entry key="entity.user_detail">User Detail</entry>
    <entry key="entity.user_photo">User Photo</entry>
    <entry key="entity.user_position">User Position</entry>
    <entry key="entity.department">Department</entry>
    <entry key="entity.ename">eName</entry>
    <entry key="entity.ework_server">eWork Server</entry>
    <entry key="entity.es_cluster">ES Cluster</entry>
    <entry key="entity.cluster">Server Cluster</entry>
    <entry key="entity.top-ename">Top-eName</entry>
    <entry key="entity.group">Virtual Server</entry>
    <entry key="entity.group_account">Virtual Server Account</entry>
    <entry key="entity.group_category">Virtual Server Category</entry>
    <entry key="entity.position">Position</entry>
    <entry key="entity.vip">VIP User</entry>
    <entry key="entity.meeting">Net Meeting</entry>
    <entry key="entity.meetingmember">Net Meeting Member</entry>
    <entry key="entity.config">Configuration Entry</entry>
    <entry key="entity.consumption">Consumption</entry>
    <entry key="entity.monthlybill">Monthly Bill</entry>
    <entry key="entity.biz_service">Biz Service</entry>
    <entry key="entity.upgrade_file">Upgrade File</entry>
    <entry key="entity.upgrade_version">Upgrade Version</entry>
    <entry key="entity.faq">FAQ</entry>
    <entry key="entity.faq_category">FAQ Category</entry>
    <entry key="entity.sms">SMS</entry>
    <entry key="entity.fenix.region">Forum Region</entry>
    <entry key="entity.fenix.urrelation">User-Forum Relation</entry>
    <entry key="entity.fenix.userinfo">User Info Of Forum</entry>
    <entry key="entity.payment">Payment</entry>

    <entry key="option.na">N/A</entry>
    <entry key="option.unlimited">Unlimited</entry>
    <entry key="option.select">Select...</entry>
    <entry key="option.dontchange">Don't Change</entry>

    <entry key="option.gender.unknown">Unknown</entry>
    <entry key="option.gender.male">Male</entry>
    <entry key="option.gender.female">Female</entry>

    <entry key="option.online.default">Default</entry>
    <entry key="option.online.online">Online</entry>
    <entry key="option.online.busy">Busy</entry>
    <entry key="option.online.away">Away</entry>
    <entry key="option.online.hidden">Offline</entry>
    <entry key="option.online.offline">Offline</entry>

    <entry key="option.publicity.private">Private</entry>
    <entry key="option.publicity.public">Public</entry>
    <entry key="option.publicity.group.private">Deny</entry>
    <entry key="option.publicity.group.public">Accept</entry>

    <entry key="option.state.normal">Normal</entry>
    <entry key="option.state.paused">Paused</entry>
    <entry key="option.state.warning">Pending-Expire</entry>
    <entry key="option.state.expired">Expired</entry>
    <entry key="option.state.open">Verifying</entry>
    <entry key="option.state.close">Open</entry>
    <entry key="option.state.na">NA</entry>

    <entry key="option.meeting.state.notstart">Unstarting</entry>
    <entry key="option.meeting.state.porcess">Process</entry>
    <entry key="option.meeting.state.end">End</entry>

    <entry key="option.archive.normal">Default Tag</entry>
    <entry key="option.archive.persistence">Permanence Hold</entry>

    <entry key="option.treenode.visible">Visible</entry>
    <entry key="option.treenode.searchable">Searchable</entry>
    <entry key="option.treenode.hidden">Hidden</entry>

    <entry key="option.friend_mode.always">Allow anyone to add me</entry>
    <entry key="option.friend_mode.verify">Always ask me when people want to add me</entry>
    <entry key="option.friend_mode.never">I prefer not to be added by others</entry>

    <entry key="option.edition.public.wan">Public (WAN)</entry>
    <entry key="option.edition.public.lan">Public (LAN)</entry>
    <entry key="option.edition.enterprise.wan">Enterprise (WAN)</entry>
    <entry key="option.edition.enterprise.lan">Enterprise (LAN)</entry>

    <entry key="option.user.root.name">Administrator</entry>

    <entry key="option.groupcate.na">n/a</entry>
    <entry key="option.groupcate.ework">eWork</entry>
    <entry key="option.groupcate.location">Location</entry>
    <entry key="option.groupcate.enterprise">Enterprise</entry>
    <entry key="option.groupcate.service">Service</entry>
    <entry key="option.groupcate.product">Product</entry>
    <entry key="option.groupcate.interest">Interest</entry>
    <entry key="option.groupcate.emotion">Emotion</entry>
    <entry key="option.groupcate.life">Life</entry>

    <entry key="option.payment">Payment</entry>

    <entry key="option.payment.currency.rmb">RMB</entry>
    <entry key="option.payment.currency.usd">USD</entry>
    <entry key="option.payment.currency.hkd">HKD</entry>
    <entry key="option.payment.currency.eur">EUR</entry>
    <entry key="option.payment.currency.jpy">JPY</entry>

    <entry key="option.payment.paymethod">Pay Method</entry>
    <entry key="option.payment.ordertime">Payment Time</entry>
    <entry key="option.payment.state">Payment State</entry>
    <entry key="option.payment.any">any</entry>

    <entry key="option.payment.paymethod.other">Other</entry>
    <entry key="option.payment.paymethod.card">eWork Card</entry>
    <entry key="option.payment.paymethod.bank">Remittance</entry>
    <entry key="option.payment.paymethod.mobile">Cell Phone</entry>
    <entry key="option.payment.paymethod.cmb">CMB</entry>
    <entry key="option.payment.paymethod.chinapay">ChinaPay</entry>

    <entry key="option.payment.paymethod.other.des">Other</entry>
    <entry key="option.payment.paymethod.card.des">eWork Card</entry>
    <entry key="option.payment.paymethod.bank.des">Remittance</entry>
    <entry key="option.payment.paymethod.mobile.des">Cell Phone</entry>
    <entry key="option.payment.paymethod.chinapay.des">ChinaPay</entry>

    <entry key="option.payment.bank.select">SELECT THE BANK AND CREDIT CARD</entry>
    <entry key="option.payment.bank.cmb">CHINA MERCHANTS BANK</entry>
    <entry key="option.payment.bank.icbc">INDUSTRIAL AND COMMERCIAL BANK OF CHINA</entry>
    <entry key="option.payment.bank.ccb">CHINA CONSTRUCTION BANK</entry>
    <entry key="option.payment.bank.abc">AGRICAULTURAL BANK OF CHINA</entry>
    <entry key="option.payment.bank.cib">INDUSTRIAL BANK CO.,LTD</entry>
    <entry key="option.payment.bank.ceb">CHINA EVERBRIGHT BANK</entry>
    <entry key="option.payment.bank.citicib">CITIC INDUSTRIAL BANK</entry>
    <entry key="option.payment.bank.cmbc">CHINA MINSHENG BANKING CORP.,LTD</entry>
    <entry key="option.payment.bank.hx">HUAXIA BANK</entry>
    <entry key="option.payment.bank.gdb">GUANDONG DEVELOPMENT BANK</entry>
    <entry key="option.payment.bank.sdb">SHENZHEN DEVELOPMENT BANK CO.,LTD</entry>
    <entry key="option.payment.bank.bocsh">BANK OF CHINA SHANGHAI BRANCH</entry>
    <entry key="option.payment.bank.commsh">BANK OF COMMUNICATIONS SHANGHAI BRANCH</entry>
    <entry key="option.payment.bank.abcsh">AGRICAULTURAL BANK OF CHINA SHANGHAI BRANCH</entry>
    <entry key="option.payment.bank.ccsh">SHANGHAI COUNTRY COMEMERCIAL BANK</entry>

    <entry key="option.payment.state.order">Unpaying</entry>
    <entry key="option.payment.state.pay">paid</entry>
    <entry key="option.payment.state.error">failure</entry>

    <entry key="option.payment.state.order.des">Unpaying</entry>
    <entry key="option.payment.state.pay.des">Paid</entry>
    <entry key="option.payment.state.unmatch">Unmatch</entry>
    <entry key="option.payment.state.error.des">Failure</entry>

    <entry key="option.payment.accountId">Account eName</entry>
    <entry key="option.payment.amount">Amount</entry>
    <entry key="option.payment.detail">Payment Details</entry>
    <entry key="option.payment.product_service">Product / Service</entry>
    <entry key="option.payment.payer">Payer</entry>
    <entry key="option.payment.actual_amount">Actual Amount</entry>

    <entry key="option.biz.renewal.false">Does not continue the expense</entry>
    <entry key="option.biz.renewal.true">Continue the expense</entry>

    <entry key="option.lu.component.client">Client</entry>
    <entry key="option.lu.component.es">eWork Socket Server</entry>
    <entry key="option.lu.component.esweb">eWork Web server</entry>

    <entry key="option.lu.operation.replace">Replace</entry>
    <entry key="option.lu.operation.remove">Remove</entry>
    <entry key="option.lu.operation.unzip">Decompress</entry>
    <entry key="option.lu.operation.exec">Execute</entry>
    <entry key="option.lu.operation.overwrite">Overwrite</entry>

    <entry key="config.conn.type">Connection Type</entry>

    <entry key="prop.age">age</entry>
    <entry key="prop.agerange">age range</entry>
    <entry key="prop.password">password</entry>
    <entry key="prop.vericode">verification code</entry>
    <entry key="prop.pwdcfm">password confirm</entry>
    <entry key="prop.user.nickname">display name</entry>
    <entry key="prop.user.realname">real name</entry>
    <entry key="prop.username">username</entry>
    <entry key="prop.ename">eName</entry>
    <entry key="prop.user.passq">password question</entry>
    <entry key="prop.user.passa">password answer</entry>
    <entry key="prop.gender">gender</entry>
    <entry key="prop.age">age</entry>
    <entry key="prop.agerange">age range</entry>
    <entry key="prop.birthday">birthday</entry>
    <entry key="prop.career">career</entry>
    <entry key="prop.email">email</entry>
    <entry key="prop.mobile">mobile phone No.</entry>
    <entry key="prop.fax">fax No.</entry>
    <entry key="prop.phone">phone No.</entry>
    <entry key="prop.phonepri">IP Trans. No. I</entry>
    <entry key="prop.phonesec">IP Trans. No. II</entry>
    <entry key="prop.friendmode">Friend Mode</entry>
    <entry key="prop.publicity">Public to eWork Center</entry>
    <entry key="prop.publicity.group">Public Register</entry>
    <entry key="prop.icq">ICQ No.</entry>
    <entry key="prop.qq">Tencent QQ No.</entry>
    <entry key="prop.msn">MSN Messenger</entry>
    <entry key="prop.idcard">identity ID.</entry>
    <entry key="prop.location">location</entry>
    <entry key="prop.country">country/region</entry>
    <entry key="prop.province">state/province</entry>
    <entry key="prop.region">city</entry>
    <entry key="prop.career ">career</entry>
    <entry key="prop.user.enterprise">organization name</entry>
    <entry key="prop.address">post address</entry>
    <entry key="prop.postcode">postcode</entry>
    <entry key="prop.hobby">hobbies &amp; interests</entry>
    <entry key="prop.description">description</entry>
    <entry key="prop.user.description">self-introduction</entry>
    <entry key="prop.state">status</entry>
    <entry key="prop.online">online status</entry>
    <entry key="prop.id">ID</entry>
    <entry key="prop.name">name</entry>
    <entry key="prop.privilege">privilege</entry>
    <entry key="prop.sortno">sort</entry>
    <entry key="prop.createtime">create time</entry>
    <entry key="prop.modifytime">update time</entry>
    <entry key="prop.lastlogintime">last login time</entry>
    <entry key="prop.expiretime">expire time</entry>
    <entry key="prop.license_code">license code</entry>
    <entry key="prop.id_prefix">eWork ID prefix</entry>
    <entry key="prop.edition">edition</entry>
    <entry key="prop.website">website</entry>
    <entry key="prop.visibility">visibility</entry>
    <entry key="prop.parentdept">Parent Department</entry>
    <entry key="prop.user.career">career</entry>
    <entry key="prop.user.income">monthly income</entry>
    <entry key="prop.user.education">education</entry>
    <entry key="prop.user.ico">ico</entry>
    <entry key="prop.version">last version</entry>
    <entry key="prop.default">default</entry>
    <entry key="prop.max">Max. {0}</entry>
    <entry key="prop.cur">Cur. {0}</entry>
    <entry key="prop.max_cluster">Max. clusters</entry>
    <entry key="prop.max_group">Max. groups</entry>
    <entry key="prop.max_user">Max. users</entry>
    <entry key="prop.cur_group">Cur. groups</entry>
    <entry key="prop.cur_user">Cur. users</entry>
    <entry key="prop.contactor">contactor</entry>
    <entry key="prop.ip">IP</entry>
    <entry key="prop.port">Port</entry>
    <entry key="prop.cs_cluster_id">CS Cluster ID</entry>
    <entry key="prop.uuid">UUID</entry>
    <entry key="prop.category">Category</entry>
    <entry key="prop.storage_capacity">Storage Capacity</entry>
    <entry key="prop.meetingid">Meeting ID</entry>
    <entry key="prop.title">Meeting Title</entry>
    <entry key="prop.starttime">Start Time</entry>
    <entry key="prop.endtime">End Time</entry>
    <entry key="prop.creator">Creator</entry>
    <entry key="prop.president">President</entry>
    <entry key="prop.membercount">Count of Meeting Member</entry>
    <entry key="prop.archive">Archive</entry>
    <entry key="prop.meetingstate">Meeting State</entry>
    <entry key="prop.user.balance">Balance</entry>
    <entry key="prop.user.minbalance">Min Balance</entry>
    <entry key="prop.consum.peernumber">Peer Number</entry>
    <entry key="prop.consum.starttime">Start Time</entry>
    <entry key="prop.consum.endtime">End Time</entry>
    <entry key="prop.consum.duration">Duration</entry>
    <entry key="prop.consum.amount">Amount</entry>
    <entry key="prop.consum.discount">Discount</entry>
    <entry key="prop.consum.chargetype">Charge Type</entry>
    <entry key="prop.consum.description">Description</entry>
    <entry key="prop.price.name">Consumption Type</entry>
    <entry key="prop.payment.accountid">Account ID</entry>
    <entry key="prop.payment.sequence_no">Sequence NO.</entry>
    <entry key="prop.payment.ordertime">Order Time</entry>
    <entry key="prop.payment.paytime">Pay Time</entry>
    <entry key="prop.payment.amount">Amount</entry>
    <entry key="prop.payment.currency">Currency</entry>
    <entry key="prop.payment.paymethod">Pay Method</entry>
    <entry key="prop.payment.state">State</entry>
    <entry key="prop.payment.description">description</entry>
    <entry key="prop.biz_service.state">User Service State</entry>
    <entry key="prop.biz_service.opentime">Open Time</entry>
    <entry key="prop.biz_service.starttime">Start Time</entry>
    <entry key="prop.biz_service.endtime">End Time</entry>
    <entry key="prop.biz_service.renewal">Renewal</entry>
    <entry key="prop.biz_service.name">Service Name</entry>
    <entry key="prop.price.unit">Unit</entry>
    <entry key="prop.price.price">Price(Kon)</entry>
    <entry key="prop.component">Component</entry>
    <entry key="prop.language">Language</entry>
    <entry key="prop.upgrade.version">Version</entry>
    <entry key="prop.path">Path</entry>
    <entry key="prop.directory">Directory</entry>
    <entry key="prop.operation">Operation</entry>
    <entry key="prop.latestversion">Current Latest Version</entry>
    <entry key="prop.lowestversion">Lowest Version Allowed</entry>
    <entry key="prop.file.length">File Size</entry>
    <entry key="prop.md5hash">MD5</entry>
	<entry key="prop.faq.title">FAQ Title</entry>
	<entry key="prop.faq.content">FAQ Content</entry>
	<entry key="prop.faq.cate">FAQ Category</entry>
	<entry key="prop.faq_cate.desc">FAQ Category Description</entry>
	<entry key="prop.faq_cate.name">FAQ Category Name</entry>
	<entry key="prop.faq.filename">FAQ File Name</entry>
    <entry key="prop.faq.filepath">Flie path</entry>
    <entry key="prop.sms.hit">Hit</entry>
    <entry key="prop.sms.zone">SMS Zone</entry>
    <entry key="prop.imgcfm">Verify Code</entry>
    <entry key="prop.region.name">Forum Name</entry>
    <entry key="prop.region.desc">Description</entry>
    <entry key="prop.region.group">Group</entry>
    <entry key="prop.region.state">State</entry>
    <entry key="prop.region.prestige">Prestige</entry>
    <entry key="prop.region.create.time">Create Time</entry>
    <entry key="prop.region.topic.count">Topic Count</entry>
    <entry key="prop.region.article.count">Article Count</entry>
    <entry key="prop.position">Position</entry>
    

    <entry key="act.login">Sign In</entry>
    <entry key="act.signup">Sign Up</entry>
    <entry key="act.ok">OK</entry>
    <entry key="act.next">next</entry>
    <entry key="act.cancel">Cancel</entry>
    <entry key="act.back">Back</entry>
    <entry key="act.reset">Reset</entry>
    <entry key="act.submit">Submit</entry>
    <entry key="act.create">Create</entry>
	<entry key="act.createupdate">Create/Update</entry>
    <entry key="act.move">Move</entry>
    <entry key="act.edit">Modify</entry>
    <entry key="act.delete">Delete</entry>
    <entry key="act.search">Search</entry>
    <entry key="act.create.dept">Create Dept.</entry>
    <entry key="act.create.user">Create User</entry>
	<entry key="act.create.mass">Create Mass</entry>
    <entry key="act.reorder">Reorder</entry>
    <entry key="act.save">Save</entry>
    <entry key="act.user.pos">Positions</entry>
    <entry key="act.user.createpos">Create Positions</entry>
    <entry key="act.user.createposlater">Later</entry>
    <entry key="act.upgrade">Upgrade</entry>
    <entry key="act.scan">Scan</entry>
    <entry key="act.setting">Settings</entry>
    <entry key="act.publish">Publish</entry>
    <entry key="act.tbop.info">info</entry>
    <entry key="act.tbop.add">add</entry>
    <entry key="act.addfrd">Add As Friend</entry>
    <entry key="act.backfrdsrch">Search More</entry>
    <entry key="act.sendinvite">Send Invitation</entry>
	<entry key="act.print">Print</entry>
    <entry key="act.repay">Repay</entry>
    <entry key="act.bank.cmb.enter">Enter China Merchants Bank</entry>
    <entry key="act.click">Click Here</entry>
    <entry key="act.bizservice.open">Open Biz Service</entry>
	<entry key="act.createcate">Create Category</entry>
	<entry key="act.csstag">CSS Taglib</entry>
	<entry key="act.preview">Preview</entry>
    <entry key="act.mngrcate">Category</entry>
    <entry key="act.send">Send</entry>
    <entry key="act.spec.send">Send</entry>
    <entry key="act.user.search">Search Friend</entry>
    <entry key="act.fenix.search">Search Forum</entry>
    <entry key="act.fenix.join">Join</entry>
    <entry key="act.fenix.secede">Secede</entry>
    <entry key="act.fenix.full">Stop join</entry>
    

    <entry key="menu.index">Index</entry>
    <entry key="menu.user">Service</entry>
    <entry key="menu.bizinfo">Biz Info</entry>
    <entry key="menu.community">Community</entry>
    <entry key="menu.download">Download</entry>
    <entry key="menu.product">Product</entry>
    <entry key="menu.coop">Cooperation</entry>

    <entry key="menu.server">eWork Server</entry>
    <entry key="menu.group">Virtual Server</entry>
    <entry key="menu.org">Organization</entry>
    <entry key="menu.admin.user">eWork User</entry>
    <entry key="menu.admin">Administrator</entry>
    <entry key="menu.meeting">Net Meeting</entry>
    <entry key="menu.cluster">Local Cluster</entry>
    <entry key="menu.time">Time</entry>
    <entry key="menu.upgrade">Upgrade Publish</entry>
    <entry key="menu.faq">FAQ Manager</entry>
    <entry key="menu.sms">SMS Manager</entry>
    <entry key="menu.feedback">Feed back</entry>		

    <entry key="menu.org.orgtree">Org. Tree</entry>
    <entry key="menu.org.users">Users</entry>
    <entry key="menu.org.positions">Positions</entry>
    <entry key="menu.payment">Payment</entry>
    <entry key="menu.payment.create">Payment Creat</entry>
    <entry key="menu.payment.balance">Balance</entry>
    <entry key="menu.payment.detail">Payment Detail</entry>
    <entry key="menu.comsumption.detail">Consumption Detail</entry>
    <entry key="menu.monthlybill.detail">Monthly Bill</entry>
    <entry key="menu.biz_service.manage">Biz Service Managenment</entry>
    <entry key="menu.region.search">Forum Search</entry>
    <entry key="menu.region.user">Users In This Forum </entry>
    <entry key="menu.region.detail">Forum Detail</entry>
    <entry key="menu.region.list">Forum List</entry>
    

    <entry key="term.public.title">eWork&amp;trade; | an instant electronic working system</entry>
    <entry key="term.faq">FAQ</entry>
    <entry key="term.contact">Contact Us</entry>
    <entry key="term.online">Oline</entry>
    <entry key="term.about">About Us</entry>
    <entry key="term.favor">Add Favorite</entry>
    <entry key="term.terms">Terms of Use</entry>
    <entry key="term.jobopp">Job Opportunity</entry>
    <entry key="term.userlogin">User Sign-in</entry>
    <entry key="term.usertype">User Type</entry>
    <entry key="term.username">Username</entry>
    <entry key="term.enamevip">eName/VIP</entry>
    <entry key="term.password">Password</entry>
    <entry key="term.verifycode">Verify</entry>
    <entry key="term.fetchpwd">Forget your password?!</entry>
    <entry key="term.user.upgrade">eWork 6.x / eLink 2005 User Account Upgrade</entry>

    <entry key="term.egadmin.title">eWork&amp;trade; | Information Center</entry>

    <entry key="term.searchform">Search</entry>

    <entry key="term.copyright">&amp;copy;1994-2005 Konlink Group, Inc. All Rights Reserved.</entry>
    <entry key="term.icp.license">ICP 证 川B2-20040081</entry>
    <entry key="term.create">Create New {0}</entry>
    <entry key="term.update">Update {0} &lt;b&gt;{1}&lt;/b&gt;</entry>

    <entry key="term.user.service">{0} Service Center</entry>
    <entry key="term.user.update">Update Info/Password</entry>
    <entry key="term.user.logout">Logout</entry>
    <entry key="term.user.account">User Account</entry>
    <entry key="term.user.search">User Search</entry>
    <entry key="term.user.searchadd">Friend Search / Add</entry>
    <entry key="term.fenix.searchadd">Forum Search / Add</entry>
    <entry key="term.user.friend.result">Friend Add Result</entry>
    <entry key="term.user.friend.invite">Invite Message</entry>

    <entry key="term.user.priphoneasmobile">Set as Mobile No.</entry>

    <entry key="term.org.org">Tree</entry>
    <entry key="term.org.user">Users</entry>
    <entry key="term.org.position">Positions</entry>
 
    <entry key="term.userreg.basicinfo">Basic Information</entry>
    <entry key="term.userreg.contactinfo">Contact Information</entry>
    <entry key="term.userreg.detailinfo">Detail Information</entry>
    <entry key="term.userreg.imbind">Integrate with eWork</entry>
	<entry key="term.massreg.privateinfo">Private information of Mass</entry>
	<entry key="term.massreg.comminfo">Common information of Mass</entry>
	<entry key="term.mass.users">Users</entry>

    <entry key="term.es.info">eWork Server &lt;b&gt;{0}&lt;/b&gt;</entry>
    <entry key="term.es.cluster">eWork Server &lt;b&gt;{0}&lt;/b&gt;'s Clusters</entry>
    <entry key="term.es.create">Create New eWork Server</entry>
    <entry key="term.es.update">Update eWork Server &lt;b&gt;{0}&lt;/b&gt;</entry>

    <entry key="term.admin.create">Create New Administrator</entry>
    <entry key="term.admin.update">Update Administrator &lt;b&gt;{0}&lt;/b&gt;</entry>
    <entry key="term.dept.create">Create New Department</entry>
    <entry key="term.dept.update">Update Department Information for &lt;b&gt;{0}&lt;/b&gt;</entry>
    <entry key="term.pos.create">Create New Position</entry>
    <entry key="term.pos.update">Update Position &lt;b&gt;{0}&lt;/b&gt;</entry>
    <entry key="term.userpos.create">Create Positions for &lt;b&gt;{0}&lt;/b&gt;</entry>
    <entry key="term.userpos.update">Update Positions for &lt;b&gt;{0}&lt;/b&gt;</entry>
    <entry key="term.treenode.move">Move Tree-Nodes</entry>
    <entry key="term.treenode.userpos">User Positions to Move</entry>
    <entry key="term.treenode.dept">Move following tree-nodes to</entry>
    <entry key="term.treenode.position">Set the position as</entry>

	<entry key="term.pubuser.title">Public Users Register</entry>
	<entry key="term.group.title">Group Register</entry>
	<entry key="term.group.reg">Register Group</entry>
	<entry key="term.group.reg.ok">Could Register!</entry>
    
    <entry key="term.biz.type.sms">SMS</entry>
    <entry key="term.biz.type.ip2phone">IP Phone</entry>
    <entry key="term.biz.type.fax">FAX</entry>
    <entry key="term.biz.price.regbonus">RegBonus</entry>
    <entry key="term.biz.price.rate.rmb">RMB Rate</entry>
    
    <entry key="term.biz.unit.item">条</entry>
    <entry key="term.biz.unit.minute">分钟</entry>
    <entry key="term.biz.unit.time">时间</entry>
    <entry key="term.biz.unit.rmb">元</entry>

	<entry key="term.faq.info">FAQ Informations</entry>
    <entry key="term.typelistform">Category List</entry>

    <entry key="tip">&lt;b&gt;Tips:&lt;/b&gt; </entry>
    <entry key="tip.help.vericode">Why should I provide the verify-code?</entry>
	<entry key="tip.help.password">How to enhance the security of my password?</entry>
	<entry key="tip.help.pwdfetch">What should I do if I forget my password?</entry>
	<entry key="tip.help.iptrans">What is IP-phone transfer No.?</entry>
	<entry key="tip.help.otherim">Why should I provide the IDs of other IM?</entry>

	<entry key="tip.vericode">Please fill the text you see in the picture</entry>
	<entry key="tip.ename">letters(a-z), digits(0-9), dashes(-) and undercores(_)</entry>
	<entry key="tip.nickname">Please offer your real name to make more efficient communication</entry>
	<entry key="tip.password">6-16 characters</entry>
    <entry key="tip.passwordupd">leave blank if no update</entry>
	<entry key="tip.pwdcfm">Please re-type the password again</entry>
	<entry key="tip.passq">the private question displayed when you forget your password &lt;b&gt;(This is REQUIRED, or your password CANNOT be fetched back when lost!)&lt;/b&gt;</entry>
	<entry key="tip.passa">the answer to the question above</entry>

	<entry key="tip.birthday">yyyy-mm-dd</entry>
	<entry key="tip.email">eg. username@domain.ext</entry>
	<entry key="tip.mobile"></entry>
	<entry key="tip.phone">028-86530481-1010 or +86-28-86530481-1011</entry>
	<entry key="tip.phonepri">can be either a mobile or a common phone No.</entry>
    <entry key="tip.from">From :</entry>
    <entry key="tip.to">To :</entry>

	<entry key="tip.realname"></entry>
	<entry key="tip.idcard">the No. of your ID. card</entry>
	<entry key="tip.hobby"></entry>
	<entry key="tip.userdesc"></entry>

    <entry key="tip.tree.busy">Getting data...</entry>
    <entry key="tip.tree.nosub">No sub-department or user found</entry>

    <entry key="tip.time">(Please enter the date，just like "200409".)</entry>
    <entry key="tip.payment.accountId">Please enter yourself eName or other eName which you want to pay for.</entry>
    <entry key="tip.payment.amount">Please enter the amount，just like "200.00", and the currency is</entry>

    <entry key="tip.reg.bonus.sms">Username: {0} Verify Code: {1}</entry>
    <entry key="tip.double.click">Double Click To Show Detail</entry>

    <entry key="para.userreg.group">Please select a virtual server you would like to register in: </entry>
    <entry key="para.userreg.regnow">Register Now</entry>
	<entry key="para.userreg.basic">The fields marked with (&lt;EM&gt;*&lt;/EM&gt;) are required, please offer true information so that you can make full use of eWork! </entry>
    <entry key="para.userreg.contact">Please provide true information of following fields, so that you and your contacts can communicate more efficiently via eWork. They won't be public to others unless you permitted! </entry>
    <entry key="para.userreg.detail">The following fields won't be public to others unless you permitted! </entry>

    <entry key="para.user.friend.rejected">Following users are not allowed to be added as friend! </entry>
    <entry key="para.user.friend.added">Following users have been added successfully! </entry>
    <entry key="para.user.friend.verify">Following users need identification before they can be added, please enter your personal information to invite them! </entry>

    <entry key="para.user.welcome">Welcome, {0}! </entry>

    <entry key="para.tree.reorder">To change the order of current tree node, select the parent department in the organization tree, then click the 'Reorder' button. </entry>
    <entry key="para.tree.move">To change to parent department of this tree node, select this node in the tree, and then click the 'Move' button. </entry>
    <entry key="para.paymethod.CMB">&lt;a href="https://www.sz1.cmbchina.com/script/PaymentApply_all.htm" target="_blank"&gt;Apply for CMB credit card.&lt;/a&gt;</entry>
    <entry key="para.paymethod.chinapay">ChinaPay</entry>
    <entry key="para.paymethod.chinapay.open">If you cannot pay for in the Internet,please apply for this business in the bank with your valid identification ,and then you could use ework service. </entry>
    <entry key="para.paymethod.chinapay.url">&lt;a href="./help/page.do?id=helpfee7" target="_blank"&gt;The supported banks.&lt;/a&gt;</entry>
    <entry key="para.paymethod.chinapay.des"><![CDATA[ <P>You can apply for on-line payment in the internet. <A HREF="https://www.sz1.cmbchina.com/script/PaymentApply_all.htm"
        target="_blank">Apply for CMB Card immediately.</A> <P>Please choose the bank and the corresponding card that you need to use for paying,and then press <font color="green">"ok"</font>，then you can pay for at the relevant bank's page.Please do not pay for it,if the order amount and the pay amount are different when you are paying for!
    <P>Please record and keep your <Font color="green">Order Number</Font> and <Font color="green">Order Time</Font>for checking in the future.]]>
    </entry>

    <entry key="para.payment.chinapay.des_1">After you apply for online-payment successfully,you can pay for at our web site.</entry>
    <entry key="para.payment.chinapay.des_2">.Show the banks, the cards which we supported and watch help demo right now.</entry>
    <entry key="para.payment.chinapay.des_3"><![CDATA[<p>Please choose the bank and the corresponding card that you need to use for paying,and then press <font color="green">"ok"</font>，then you can pay for at the relevant bank's page.Please do not pay for it,if the order amount and the pay amount are different when you are paying for!
    <P>Please record and keep your <Font color="green">Order Number</Font> and <Font color="green">Order Time</Font>for checking in the future.]]>
    </entry>
    <entry key="para.monthlybill.description"><![CDATA[1. This bill is convenient for you to find out about your own telephone expenses expenditure situation.If there is doubt, please dial the customer service number +86-28-86530481-1026.<br>2. If there is doubt, please dial the customer service number +86-28-86530481-1026 in order to guarantee bills can send to you in time , please log in in time while changing your infomation at <A href="http://www.konlink.net">www.konlink.net</A> or dialing +86-28-86530481-1026 to upgrade. <br>3. The charging unit of the long-distance fee of IP is minute. <br>]]>
    </entry>

    <entry key="para.bizserivce.mgr1">Open service which you need.</entry>
    <entry key="para.bizserivce.mgr2">Open services in batches.</entry>
    <entry key="para.bizserivce.edit">You can edit your biz service which have been opened.</entry>

    <entry key="para.upgrade.upload.p1">1. Please upload all the upgrade files of this version to the path {0} on Socket Server, keep the paths as they would be published.</entry>
    <entry key="para.upgrade.upload.p2">2. Please upload the installation package to download site in path {0}</entry>
    <entry key="para.upgrade.upload.p3">3. Click the "Submit" button, the system will begin to scan the files you uploaded. You have to go to "Settings" to set the operations should be done when files are downloaded. </entry>
    <entry key="para.upgrade.upload.p4">4. "Publish" the version on version browsing page. </entry>

    <!-- Tag Text -->
    <entry key="tag.navigator.listrange">&lt;b&gt;{0}&lt;/b&gt; entry(s) in totle, No. &lt;b&gt;{1} - {2}&lt;/b&gt; are displayed in this page.</entry>
    <entry key="tag.navigator.pages">Page &lt;b&gt;{0} / {1}&lt;/b&gt;</entry>
    <entry key="tag.navigator.btn.first">First</entry>
    <entry key="tag.navigator.btn.prev">Previous</entry>
    <entry key="tag.navigator.btn.next">Next</entry>
    <entry key="tag.navigator.btn.last">Last</entry>

    <!-- Form Text-->
    <entry key="form.search.month">Search Month</entry>
    <entry key="form.region.search>">Search String</entry>

    <!--report Text -->
    <entry key="report.description">Description</entry>
    <entry key="report.account">Account Name:</entry>
    <entry key="report.duration">Duration:</entry>
    <entry key="report.duration_content">{0} to {1}</entry>
    <entry key="report.print_time">Print Time:</entry>
    <entry key="report.total_amount">Total Amount</entry>
    <entry key="report.monthlybill.title">Monthly Bill</entry>
    <entry key="report.monthlybill.biztype">Consumption</entry>
    <entry key="report.monthlybill.pricevalue"><![CDATA[ Traffic&nbsp;&nbsp;&nbsp;&nbsp;&nbsp;Price&nbsp;&nbsp;&nbsp;&nbsp;Subtotal
                                                      <BR>
                                                      (time/piece)&nbsp;(Kon)&nbsp;(Kon)]]>
    </entry>
    <entry key="report.monthlybill.total_dicount">Total Discount</entry>
    <entry key="report.monthlybill.actual_amount">Actual Amount</entry>
    <entry key="report.monthlybill.balance"><![CDATA[ &nbsp;Until {0}，your balance remain {1}.]]></entry>

    <!--Biz Text  -->
    <entry key="biz.dotService">Dot Service</entry>
    <entry key="biz.durService">Duration Service</entry>
    <entry key="biz.dot.sms">message</entry>
    <entry key="biz.dot.mms">mms</entry>
    <entry key="biz.dur.phone">phone</entry>
    <entry key="biz.dur.ip">IP phone</entry>
    <entry key="biz.dot.aa">dot test 1</entry>
    <entry key="biz.dot.bb">dot test 2</entry>
    <entry key="biz.dur.aa">dur test 1</entry>


    <!--Group Text-->
    <entry key="group.group_name">Group Name</entry>
    <entry key="group.group_desc">Group Description</entry>
    <entry key="group.group_cata">Group Category</entry>
    <entry key="group.group_max_cata">Main Category</entry>
    <entry key="group.group_min_cata">Sub Category</entry>
    <entry key="group.group_enter_key">Enter Keywords</entry>
    <entry key="group.group_key_tip">You can enter keywords to find this group more quickly and efficient. (5 limited)</entry>
    <entry key="group.group_join_mode">Join mode</entry>
    <entry key="group.group_join_1">Anyone can join this group at will. (public)</entry>
    <entry key="group.group_join_2">Anyone must obtain permission from the administrator to join. (permission)</entry>
    <entry key="group.group_join_3">Only the person which had invited can join this group. (hidden)</entry>
    <entry key="group.group_member_count">Members:</entry>
    <entry key="group.group_admin">Group Admin:</entry>
    <entry key="group.group_creator">Group Creator:</entry>
    <entry key="group.group_create_time">Group Create Time:</entry>
    <entry key="group.group_description">Group Description:</entry>

    <entry key="group.leftbar.create">Create new group</entry>
    <entry key="group.leftbar.browse">Browse the groups</entry>
    <entry key="group.leftbar.search">Search groups</entry>
    <entry key="group.leftbar.back">Go Back</entry>

    <entry key="group.join.memberscount">has members: </entry>
    <entry key="group.join.createby">, created by </entry>
    <entry key="group.join.createat">at </entry>
    <entry key="group.join.button"> Join Now </entry>
    <entry key="group.join.passwd"> You can't join this group now unless have the password of this group. </entry>

    <entry key="group.button.search">Search</entry>
    <entry key="group.tip.search">Group Search: </entry>
    <entry key="group.title.create">Create Group</entry>
    <entry key="group.title.group_count">Groups stat</entry>
    <entry key="group.title.group_name">Group Category</entry>
    <entry key="group.title.id">Id</entry>
	<entry key="group.title.join">Join Group</entry>
    <entry key="group.title.search">Search Group</entry>
    <entry key="group.title.sub_category">Sub group categories belong to {0}</entry>

    <!--state -->
    <entry key="state.fenix.region.joined">Could Join</entry>
    <entry key="state.fenix.region.joined">Full</entry>
    <entry key="state.fenix.user.joined"><![CDATA[ <font class="green">Joined</font>]]></entry>
    <entry key="state.fenix.user.seceded"><![CDATA[<font class="red">Unjoined</font>]]></entry>
    
    
    <!--script tip message -->
    <entry key="script.user.del">Are you sure to delete the current user?</entry>
    <entry key="script.dep.del">Are you sure to delete the selected departments?</entry>
    <entry key="script.admin.del">Are you sure to delete the current administrator?</entry>
    <entry key="script.mobiles.exist">Mobiles exist!</entry>
    <entry key="script.mobiles.number.error">Not right format!</entry>
    <entry key="script.forum.del">Secede from this forum, will delete your forum's fiends!</entry>
</properties>